tencentcloud/__init__.py
tencentcloud/vod/__init__.py
tencentcloud/vod/v20180717/__init__.py
tencentcloud/vod/v20180717/errorcodes.py
tencentcloud/vod/v20180717/models.py
tencentcloud/vod/v20180717/vod_client.py
tencentcloud/vod/v20180717/vod_client_async.py
tencentcloud/vod/v20240718/__init__.py
tencentcloud/vod/v20240718/errorcodes.py
tencentcloud/vod/v20240718/models.py
tencentcloud/vod/v20240718/vod_client.py
tencentcloud/vod/v20240718/vod_client_async.py
tencentcloud_sdk_python_vod-3.1.32.dist-info/METADATA
tencentcloud_sdk_python_vod-3.1.32.dist-info/WHEEL
tencentcloud_sdk_python_vod-3.1.32.dist-info/top_level.txt
tencentcloud_sdk_python_vod-3.1.32.dist-info/RECORD
